shalinee_pattern_package/__init__.py
shalinee_pattern_package/pattern.py
shalinee_pattern_package-0.1.2.dist-info/licenses/LICENSE
shalinee_pattern_package-0.1.2.dist-info/METADATA
shalinee_pattern_package-0.1.2.dist-info/WHEEL
shalinee_pattern_package-0.1.2.dist-info/top_level.txt
shalinee_pattern_package-0.1.2.dist-info/RECORD
