Metadata-Version: 2.4
Name: shalinee_pattern_package
Version: 0.1.2
Summary: This package is for printing patterns
Home-page: https://github.com/Shalinee-Priya/pattern
Author: Shalinee
Author-email: shalinee.priya31@gmail.com
Classifier: Programming Language :: Python :: 3
Classifier: License :: OSI Approved :: MIT License
Classifier: Operating System :: OS Independent
Requires-Python: >=3.6
License-File: LICENSE
Dynamic: author
Dynamic: author-email
Dynamic: classifier
Dynamic: description
Dynamic: description-content-type
Dynamic: home-page
Dynamic: license-file
Dynamic: requires-python
Dynamic: summary
